<?xml version="1.0" encoding="utf-8" standalone="yes"?>
<Calibracion>
  <NroCertificado></NroCertificado>
  <FechaDeCalibracion></FechaDeCalibracion>
  <FechaEmisionCertificado></FechaEmisionCertificado>
  <Instalacao></Instalacao>
  <Tipo>DPT</Tipo>
  <Serial>0289793</Serial>
  <FajaInicial>0,00</FajaInicial>
  <FajaFinal>60,00</FajaFinal>
  <InLoco>1</InLoco>
  <AsLeft>0</AsLeft>
  <CalcularValorNominal>0</CalcularValorNominal>
  <TAG>FIT-1231010A</TAG>
  <GrillaAsFound>
    <ValorNominal>0,00</ValorNominal>
    <MediaInstrumento>0,002</MediaInstrumento>
    <Tendencia>-0,002</Tendencia>
    <Incerteza>0,00</Incerteza>
    <K>0,00</K>
  </GrillaAsFound>
  <GrillaAsFound>
    <ValorNominal>15,000</ValorNominal>
    <MediaInstrumento>15,032</MediaInstrumento>
    <Tendencia>-0,032</Tendencia>
    <Incerteza>0,024</Incerteza>
    <K>2,01</K>
  </GrillaAsFound>
  <GrillaAsFound>
    <ValorNominal>30,000</ValorNominal>
    <MediaInstrumento>30,008</MediaInstrumento>
    <Tendencia>-0,008</Tendencia>
    <Incerteza>0,03</Incerteza>
    <K>2,01</K>
  </GrillaAsFound>
  <GrillaAsFound>
    <ValorNominal>45,000</ValorNominal>
    <MediaInstrumento>45,030</MediaInstrumento>
    <Tendencia>-0,03</Tendencia>
    <Incerteza>0,03</Incerteza>
    <K>2,01</K>
  </GrillaAsFound>
  <GrillaAsFound>
    <ValorNominal>60,000</ValorNominal>
    <MediaInstrumento>60,018</MediaInstrumento>
    <Tendencia>-0,018</Tendencia>
    <Incerteza>0,03</Incerteza>
    <K>2,01</K>
  </GrillaAsFound>
  </Calibracion>
